{
  "name": "benny9193-code-patterns",
  "source": "./plugins/benny9193/code-patterns",
  "description": "Common code patterns and best practices reference for quick lookup",
  "version": "1.0.0",
  "author": {
    "name": "Benny9193"
  },
  "repository": "https://github.com/Benny9193/devflow/tree/master/skills/code-patterns",
  "license": "MIT",
  "keywords": [
    "design-patterns",
    "software-architecture",
    "typescript",
    "best-practices",
    "reference"
  ],
  "category": "coding",
  "tags": [
    "design-patterns",
    "software-architecture",
    "typescript",
    "best-practices",
    "reference"
  ]
}
