{
  "name": "autumnsgrove-pdf",
  "source": "./plugins/autumnsgrove/pdf",
  "description": "Comprehensive PDF manipulation, extraction, and generation with support for text extraction, form filling, merging, splitting, annotations, and creation. Use when working with .pdf files for: (1) Extracting text and tables, (2) Filling PDF forms, (3) Merging/splitting PDFs, (4) Creating PDFs programmatically, (5) Adding watermarks/annotations, (6) PDF metadata management",
  "version": "1.0.0",
  "author": {
    "name": "AutumnsGrove"
  },
  "repository": "https://github.com/AutumnsGrove/ClaudeSkills/tree/master/pdf",
  "license": "MIT",
  "keywords": [
    "PDF",
    "Python",
    "document processing",
    "text extraction",
    "OCR"
  ],
  "category": "documentation",
  "tags": [
    "PDF",
    "Python",
    "document processing",
    "text extraction",
    "OCR"
  ]
}
